link_checker/__init__.py
link_checker/_version.py
link_checker/cli.py
link_checker/main.py
rms_link_checker-1.0.0.dist-info/LICENSE
rms_link_checker-1.0.0.dist-info/METADATA
rms_link_checker-1.0.0.dist-info/WHEEL
rms_link_checker-1.0.0.dist-info/entry_points.txt
rms_link_checker-1.0.0.dist-info/top_level.txt
rms_link_checker-1.0.0.dist-info/RECORD
