Metadata-Version: 2.2
Name: rms-link-checker
Version: 1.0.0
Summary: A tool for checking broken links and cataloging internal assets on websites
Maintainer-email: "Robert S. French" <rfrench@seti.org>
License: Apache-2.0
Project-URL: Homepage, https://github.com/SETI/rms-link-checker
Project-URL: Documentation, https://rms-link-checker.readthedocs.io/en/latest
Project-URL: Repository, https://github.com/SETI/rms-link-checker
Project-URL: Source, https://github.com/SETI/rms-link-checker
Project-URL: Issues, https://github.com/SETI/rms-link-checker/issues
Keywords: link checker
Classifier: Development Status :: 5 - Production/Stable
Classifier: Natural Language :: English
Classifier: Topic :: Utilities
Classifier: License :: OSI Approved :: Apache Software License
Classifier: Programming Language :: Python :: 3.8
Classifier: Programming Language :: Python :: 3.9
Classifier: Programming Language :: Python :: 3.10
Classifier: Programming Language :: Python :: 3.11
Classifier: Programming Language :: Python :: 3.12
Classifier: Programming Language :: Python :: 3.13
Classifier: Operating System :: MacOS :: MacOS X
Classifier: Operating System :: POSIX :: Linux
Classifier: Operating System :: Microsoft :: Windows
Requires-Python: >=3.8
License-File: LICENSE
Requires-Dist: beautifulsoup4
Requires-Dist: colorama
Requires-Dist: requests
